[
  {
    "id": 1,
    "jobTitle": "Senior Software Developer | Backend | Remote in the USA",
    "jobDescription": "Moz is looking for a Senior Software Developer to join our Application Development team.",
    "department": "Engineering",
    "type": "Application Development"
  },
  {
    "id": 2,
    "jobTitle": "Senior Software Developer | Backend | Remote in the USA",
    "jobDescription": "Moz is looking for a Senior Software Developer to join our Application Development team.",
    "department": "Engineering",
    "type": "Application Development"
  },
  {
    "id": 3,
    "jobTitle": "Senior Software Developer | Backend | Remote in the USA",
    "jobDescription": "Moz is looking for a Senior Software Developer to join our Application Development team.",
    "department": "Engineering",
    "type": "Application Development"
  },
  {
    "id": 4,
    "jobTitle": "Senior Software Developer | Backend | Remote in the USA",
    "jobDescription": "Moz is looking for a Senior Software Developer to join our Application Development team.",
    "department": "Engineering",
    "type": "Application Development"
  },
  {
    "id": 5,
    "jobTitle": "Senior Software Developer | Backend | Remote in the USA",
    "jobDescription": "Moz is looking for a Senior Software Developer to join our Application Development team.",
    "department": "Engineering",
    "type": "Application Development"
  },
  {
    "id": 6,
    "jobTitle": "Senior Software Developer | Backend | Remote in the USA",
    "jobDescription": "Moz is looking for a Senior Software Developer to join our Application Development team.",
    "department": "Engineering",
    "type": "Application Development"
  },
  {
    "id": 7,
    "jobTitle": "Senior Software Developer | Backend | Remote in the USA",
    "jobDescription": "Moz is looking for a Senior Software Developer to join our Application Development team.",
    "department": "Engineering",
    "type": "Application Development"
  },
  {
    "id": 8,
    "jobTitle": "Senior Software Developer | Backend | Remote in the USA",
    "jobDescription": "Moz is looking for a Senior Software Developer to join our Application Development team.",
    "department": "Engineering",
    "type": "Application Development"
  },
  {
    "id": 9,
    "jobTitle": "Senior Software Developer | Backend | Remote in the USA",
    "jobDescription": "Moz is looking for a Senior Software Developer to join our Application Development team.",
    "department": "Engineering",
    "type": "Application Development"
  },
  {
    "id": 10,
    "jobTitle": "Senior Software Developer | Backend | Remote in the USA",
    "jobDescription": "Moz is looking for a Senior Software Developer to join our Application Development team.",
    "department": "Engineering",
    "type": "Application Development"
  },
  {
    "id": 11,
    "jobTitle": "Senior Software Developer | Backend | Remote in the USA",
    "jobDescription": "Moz is looking for a Senior Software Developer to join our Application Development team.",
    "department": "Engineering",
    "type": "Application Development"
  },
  {
    "id": 12,
    "jobTitle": "Senior Software Developer | Backend | Remote in the USA",
    "jobDescription": "Moz is looking for a Senior Software Developer to join our Application Development team.",
    "department": "Engineering",
    "type": "Application Development"
  }
]
